{
  "name": "tachyons",
  "description": "Functional CSS for humans",
  "main": "css/tachyons.css",
  "authors": [
    "mrmrs"
  ],
  "license": "MIT",
  "keywords": [
    "css",
    "design",
    "system",
    "responsive",
    "design"
  ],
  "homepage": "http://tachyons.io",
  "ignore": [
    "**/.*",
    "node_modules",
    "bower_components",
    "test",
    "tests"
  ],
  "version": "4.11.1",
  "_release": "4.11.1",
  "_resolution": {
    "type": "version",
    "tag": "v4.11.1",
    "commit": "f7133456466fd194e854a6dcae78da9e43cd109f"
  },
  "_source": "https://github.com/tachyons-css/tachyons.git",
  "_target": "4.11.1",
  "_originalSource": "tachyons"
}